NagAconda/Plugin.py
NagAconda/__init__.py
NagAconda-0.3.5.dist-info/LICENSE
NagAconda-0.3.5.dist-info/METADATA
NagAconda-0.3.5.dist-info/WHEEL
NagAconda-0.3.5.dist-info/top_level.txt
NagAconda-0.3.5.dist-info/RECORD
