Metadata-Version: 2.1
Name: NagAconda
Version: 0.3.5
Summary: NagAconda is a Python Nagios wrapper.
Home-page: https://github.com/SchlegelS0208/NagAconda
Author: Steven Schlegel
Author-email: steven@schlegel.tech
License: New BSD License
Platform: any
Classifier: Development Status :: 4 - Beta
Classifier: Environment :: Console
Classifier: Intended Audience :: Developers
Classifier: Intended Audience :: System Administrators
Classifier: License :: OSI Approved :: BSD License
Classifier: Operating System :: OS Independent
Classifier: Programming Language :: Python
Classifier: Topic :: Documentation
Classifier: Topic :: Software Development :: Libraries
Classifier: Topic :: System :: Monitoring
Classifier: Topic :: System :: Systems Administration
Classifier: Topic :: Utilities
License-File: LICENSE
Requires-Dist: Sphinx
